setup.cfg
setup.py
sentry_notify_hipchat/__init__.py
sentry_notify_hipchat/plugin.py
sentry_notify_hipchat.egg-info/PKG-INFO
sentry_notify_hipchat.egg-info/SOURCES.txt
sentry_notify_hipchat.egg-info/dependency_links.txt
sentry_notify_hipchat.egg-info/entry_points.txt
sentry_notify_hipchat.egg-info/requires.txt
sentry_notify_hipchat.egg-info/top_level.txt