Metadata-Version: 1.0
Name: sentry-notify-hipchat
Version: 0.1.4
Summary: A Sentry notification plugin for HipChat
Home-page: https://github.com/eagletmt/sentry-notify-hipchat
Author: Kohei Suzuki
Author-email: eagletmt@gmail.com
License: MIT
Platform: UNKNOWN
